[
  {
    "id": "dojo",
    "name": "Dojo",
    "class": "active",
    "children": [
      {
        "id": "dojo-html",
        "name": "example",
        "class": ""
      },
      {
        "id": "dojo-md",
        "name": "document",
        "class": ""
      }
    ]
  },
  {
    "id": "digit",
    "name": "Digit",
    "class": "",
    "children": [
      {
        "id": "digit-html",
        "name": "example",
        "class": ""
      },
      {
        "id": "digit-md",
        "name": "document",
        "class": ""
      }
    ]
  },
  {
    "id": "dojox",
    "name": "Dojox",
    "class": "",
    "children": []
  },
  {
    "id": "util",
    "name": "Util",
    "class": "",
    "children": []
  },
  {
    "id": "example",
    "name": "Example",
    "link": "",
    "class": "",
    "children": [
      {
        "id": "example-flat",
        "name": "flat",
        "link": "/flat.html"
      },
      {
        "id": "example-tree",
        "name": "Tree",
        "link": "",
        "children": [
          {
            "id": "example-tree-notes",
            "name": "笔记",
            "link": "/notes/tree.md"
          },
          {
            "id": "example-tree-programmatic",
            "name": "programmatic",
            "link": "/example/tree/programmatic.html"
          },
          {
            "id": "example-tree-markup",
            "name": "markup",
            "link": "/example/tree/markup.html"
          },
          {
            "id": "example-tree-crud",
            "name": "crud",
            "link": "/example/tree/crud.html"
          }
        ]
      }
    ]
  }
]